{"cameraMode":{"drawMode":0,"name":"Shaded","section":"Shading Mode"},"sceneLighting":true,"audioPlay":false,"sceneViewState":{"m_AlwaysRefresh":false,"showFog":true,"showSkybox":true,"showFlares":true,"showImageEffects":true,"showParticleSystems":true,"showVisualEffectGraphs":true,"m_FxEnabled":true},"in2DMode":false,"pivot":{"x":1.8948899507522584,"y":18.437318801879884,"z":-22.255704879760743},"rotation":{"x":-0.33560487627983096,"y":-0.017815465107560159,"z":0.0063465554267168049,"w":-0.9418173432350159},"size":6.4825215339660648,"orthographic":false}